wearipedia/__init__.py
wearipedia/__main__.py
wearipedia/cl_parser.py
wearipedia/devices/__init__.py
wearipedia/devices/apple/apple_gen.py
wearipedia/devices/apple/healthkit.py
wearipedia/devices/biostrap/evo.py
wearipedia/devices/biostrap/evo_fetch.py
wearipedia/devices/biostrap/evo_gen.py
wearipedia/devices/coros/coros_pace_2.py
wearipedia/devices/coros/coros_pace_2_fetch.py
wearipedia/devices/coros/coros_pace_2_gen.py
wearipedia/devices/cronometer/cronometer.py
wearipedia/devices/cronometer/cronometer_fetch.py
wearipedia/devices/cronometer/cronometer_synthetic.py
wearipedia/devices/cronometer/servings.csv
wearipedia/devices/device.py
wearipedia/devices/dexcom/pro_cgm.py
wearipedia/devices/dexcom/pro_cgm_fetch.py
wearipedia/devices/dexcom/pro_cgm_gen.py
wearipedia/devices/dreem/dreem_fetch.py
wearipedia/devices/dreem/dreem_gen.py
wearipedia/devices/dreem/headband_2.py
wearipedia/devices/fitbit/fitbit_authenticate.py
wearipedia/devices/fitbit/fitbit_charge4_fetch.py
wearipedia/devices/fitbit/fitbit_charge_4.py
wearipedia/devices/fitbit/fitbit_charge_4_gen.py
wearipedia/devices/fitbit/fitbit_charge_6.py
wearipedia/devices/fitbit/fitbit_sense.py
wearipedia/devices/fitbit/fitbit_sense_fetch.py
wearipedia/devices/fitbit/fitbit_sense_gen.py
wearipedia/devices/fitbit/google_pixel_watch.py
wearipedia/devices/garmin/fenix_7s.py
wearipedia/devices/garmin/fenix_fetch.py
wearipedia/devices/garmin/fenix_gen.py
wearipedia/devices/garmin/fenix_gen_1.py
wearipedia/devices/garmin/fenix_gen_2.py
wearipedia/devices/garmin/fenix_gen_3.py
wearipedia/devices/google/googlefit.py
wearipedia/devices/google/googlefitness_fetch.py
wearipedia/devices/google/googlefitness_synthetic.py
wearipedia/devices/myfitnesspal/myfitnesspal.py
wearipedia/devices/myfitnesspal/myfitnesspal_fetch.py
wearipedia/devices/myfitnesspal/myfitnesspal_syn_data.json
wearipedia/devices/myfitnesspal/myfitnesspal_synthetic.py
wearipedia/devices/nutrisense/cgm.py
wearipedia/devices/nutrisense/cgm_fetch.py
wearipedia-0.1.7.dist-info/LICENSE
wearipedia-0.1.7.dist-info/METADATA
wearipedia-0.1.7.dist-info/WHEEL
wearipedia-0.1.7.dist-info/entry_points.txt
wearipedia-0.1.7.dist-info/RECORD
