Metadata-Version: 2.3
Name: wearipedia
Version: 0.1.7
Summary: Wearable data for all
License: MIT
Author: The Stanford Wearipedia Project
Author-email: <arjo@stanford.edu>
Requires-Python: >=3.10, <3.13
Classifier: Development Status :: 3 - Alpha
Classifier: Intended Audience :: Developers
Classifier: Operating System :: OS Independent
Classifier: Topic :: Software Development :: Libraries :: Python Modules
Classifier: License :: OSI Approved :: MIT License
Classifier: Programming Language :: Python :: 3
Requires-Dist: beautifulsoup4 (>=4.12.2)
Requires-Dist: fastapi (==0.101)
Requires-Dist: fbm (>=0.3.0)
Requires-Dist: garminconnect (>=0.2.25)
Requires-Dist: garth (>=0.5.2)
Requires-Dist: jupyter (>=1.0.0)
Requires-Dist: myfitnesspal (>=2.0.1)
Requires-Dist: numpy (>=2.0.0)
Requires-Dist: pandas (>=2.2.2)
Requires-Dist: polyline (>=2.0.0)
Requires-Dist: qualtricsapi (>=0.6.1)
Requires-Dist: rich (>=12.6.0)
Requires-Dist: scipy (>=1.13.0)
Requires-Dist: tqdm (>=4.64.1)
Requires-Dist: typer[all] (>=0.6.1)
Requires-Dist: typing-extensions (>=4.12.2)
Requires-Dist: wget (>=3.2)
